torrra/__init__.py
torrra/__main__.py
torrra/_types.py
torrra/_version.py
torrra/app.py
torrra/app.tcss
torrra/core/__init__.py
torrra/core/cache.py
torrra/core/config.py
torrra/core/constants.py
torrra/core/db.py
torrra/core/download.py
torrra/core/exceptions.py
torrra/core/torrent.py
torrra/indexers/__init__.py
torrra/indexers/base.py
torrra/indexers/jackett.py
torrra/indexers/prowlarr.py
torrra/screens/__init__.py
torrra/screens/home.py
torrra/screens/theme_selector.py
torrra/screens/welcome.py
torrra/utils/__init__.py
torrra/utils/fs.py
torrra/utils/helpers.py
torrra/utils/indexer.py
torrra/utils/magnet.py
torrra/widgets/__init__.py
torrra/widgets/data_table.py
torrra/widgets/details_panel.py
torrra/widgets/downloads.py
torrra/widgets/search.py
torrra/widgets/sidebar.py
torrra/widgets/spinner.py
torrra-2.0.5.dist-info/METADATA
torrra-2.0.5.dist-info/WHEEL
torrra-2.0.5.dist-info/entry_points.txt
torrra-2.0.5.dist-info/licenses/LICENSE
torrra-2.0.5.dist-info/RECORD
