Metadata-Version: 2.4
Name: torrra
Version: 2.0.5
Summary: A Python tool that lets you find and download torrents without leaving your CLI.
Project-URL: homepage, https://github.com/stabldev/torrra
Project-URL: repository, https://github.com/stabldev/torrra
Project-URL: Bug Tracker, https://github.com/stabldev/torrra/issues
Author-email: stabldev <thestabldev@gmail.com>
License: MIT
License-File: LICENSE
Keywords: cli,download,filesharing,jackett,libtorrent,magnet,p2p,terminal,textual,torrent,torrent-client,torrent-search,tui
Classifier: Development Status :: 5 - Production/Stable
Classifier: Environment :: Console
Classifier: Environment :: Console :: Curses
Classifier: Intended Audience :: Developers
Classifier: Intended Audience :: End Users/Desktop
Classifier: License :: OSI Approved :: MIT License
Classifier: Natural Language :: English
Classifier: Operating System :: OS Independent
Classifier: Programming Language :: Python :: 3
Classifier: Programming Language :: Python :: 3.10
Classifier: Programming Language :: Python :: 3.11
Classifier: Programming Language :: Python :: 3.12
Classifier: Programming Language :: Python :: 3.13
Classifier: Programming Language :: Python :: 3.14
Classifier: Topic :: Communications :: File Sharing
Classifier: Topic :: Terminals
Classifier: Topic :: Terminals :: Terminal Emulators/X Terminals
Requires-Python: >=3.10
Requires-Dist: click>=8.3.0
Requires-Dist: diskcache>=5.6.3
Requires-Dist: httpx>=0.28.1
Requires-Dist: libtorrent-windows-dll>=0.0.3
Requires-Dist: libtorrent>=2.0.11
Requires-Dist: platformdirs>=4.5.0
Requires-Dist: textual>=6.5.0
Requires-Dist: tomli-w>=1.2.0
Provides-Extra: docs
Requires-Dist: myst-parser>=4.0.1; extra == 'docs'
Requires-Dist: qiskit-sphinx-theme>=2.0.0; extra == 'docs'
Requires-Dist: sphinx-copybutton>=0.5.2; extra == 'docs'
Requires-Dist: sphinx<9,>=8; extra == 'docs'
